m3u8down/Error.py
m3u8down/__init__.py
m3u8down/m3u8_5.py
test-a/__init__.py
m3u8down-0.5.4.dist-info/METADATA
m3u8down-0.5.4.dist-info/WHEEL
m3u8down-0.5.4.dist-info/top_level.txt
m3u8down-0.5.4.dist-info/RECORD
